README.txt
setup.cfg
setup.py
abcd.egg-info/PKG-INFO
abcd.egg-info/SOURCES.txt
abcd.egg-info/dependency_links.txt
abcd.egg-info/requires.txt
abcd.egg-info/top_level.txt
digger/__init__.py
digger/actions.py
digger/config.py
digger/errors.py
digger/parser.py
digger/base/__init__.py
digger/base/action.py
digger/base/build.py
digger/builds/__init__.py
digger/builds/ant.py
digger/builds/cordova_android.py
digger/builds/gradle.py
digger/helpers/__init__.py
digger/helpers/android.py
digger/helpers/common.py
scripts/abcd
tests/__init__.py
tests/conftest.py
tests/test_build.py
tests/test_simple_action.py
tests/test_smoke_parse.py