Metadata-Version: 1.1
Name: abcd
Version: 0.3.0
Summary: AeroGear Build Cli for Digger
Home-page: https://github.com/aerogear/digger-build-cli
Author: AeroGear
Author-email: aerogear-dev@lists.jboss.org
License: LICENSE
Download-URL: https://github.com/aerogear/digger-build-cli/tarball/0.3.0
Keywords: application builds,gradle,ant,cordova,cli
Platform: UNKNOWN
Classifier: License :: OSI Approved :: Apache Software License
Classifier: Environment :: Console
Classifier: Topic :: Software Development :: Build Tools
